rawsock/__init__.py
rawsock/rawsocket.py
rawsock-0.0.4.dist-info/licenses/LICENSE.md
rawsock-0.0.4.dist-info/METADATA
rawsock-0.0.4.dist-info/WHEEL
rawsock-0.0.4.dist-info/top_level.txt
rawsock-0.0.4.dist-info/RECORD
