Metadata-Version: 2.4
Name: rawsock
Version: 0.0.4
Summary: a low level python implementation of a raw socket interface for sending Ethernet frames using Berkeley Packet Filters (BPF) on BSD based systems.
Author-email: 1fadi <1fadi@proton.me>
License: MIT License
Project-URL: Homepage, https://github.com/1fadi/rawsocket
Project-URL: Issues, https://github.com/1fadi/rawsocket/issues
Classifier: Programming Language :: Python :: 3
Classifier: License :: OSI Approved :: MIT License
Requires-Python: >=3.7
License-File: LICENSE.md
Dynamic: license-file
